libtorrent.pyd
deluge_libtorrent-1.1.13.dist-info/METADATA
deluge_libtorrent-1.1.13.dist-info/WHEEL
deluge_libtorrent-1.1.13.dist-info/top_level.txt
deluge_libtorrent-1.1.13.dist-info/RECORD
