Metadata-Version: 2.1
Name: deluge-libtorrent
Version: 1.1.13
Summary: Python bindings for libtorrent-rasterbar
Home-page: http://libtorrent.org
Author: Arvid Norberg
Author-email: arvid@libtorrent.org
License: BSD
Platform: Windows-AMD64
